cli.py
sl_optimizer/__init__.py
sl_optimizer/constants.py
sl_optimizer/core.py
sl_optimizer/errors.py
sl_optimizer/layout.py
sl_optimizer/utils.py
sl_optimizer-0.0.4.dist-info/LICENSE.txt
sl_optimizer-0.0.4.dist-info/METADATA
sl_optimizer-0.0.4.dist-info/WHEEL
sl_optimizer-0.0.4.dist-info/entry_points.txt
sl_optimizer-0.0.4.dist-info/top_level.txt
sl_optimizer-0.0.4.dist-info/RECORD
