Metadata-Version: 2.1
Name: sl_optimizer
Version: 0.0.4
Summary: Optimizing the arrangement of data in storage layout.
Author-email: Vladyslav Novotnyi <psejjkuczo@proxiedmail.com>
Maintainer-email: Vladyslav Novotnyi <psejjkuczo@proxiedmail.com>
License: The MIT License (MIT)
Project-URL: Homepage, https://github.com/fabelx/storage-layout-optimizer
Project-URL: Bug Reports, https://github.com/fabelx/storage-layout-optimizer/issues
Project-URL: Say Thanks!, https://saythanks.io/to/daprostovseeto
Project-URL: Source, https://github.com/fabelx/storage-layout-optimizer
Keywords: evm,solidity,storage-layout
Classifier: Development Status :: 2 - Pre-Alpha
Classifier: Intended Audience :: Developers
Classifier: License :: OSI Approved :: MIT License
Classifier: Operating System :: OS Independent
Classifier: Programming Language :: Python :: 3
Classifier: Programming Language :: Python :: 3.10
Classifier: Programming Language :: Python :: 3.11
Classifier: Programming Language :: Python :: 3.12
Classifier: Programming Language :: Python :: 3.13
Classifier: Programming Language :: Python :: 3 :: Only
Requires-Python: >=3.10
License-File: LICENSE.txt
Requires-Dist: jsonschema
Provides-Extra: dev
Requires-Dist: sl-optimizer[test] ; extra == 'dev'
Requires-Dist: sl-optimizer[lint] ; extra == 'dev'
Requires-Dist: build ; extra == 'dev'
Requires-Dist: pre-commit ; extra == 'dev'
Provides-Extra: lint
Requires-Dist: black >=23.10.0 ; extra == 'lint'
Requires-Dist: isort ; extra == 'lint'
Requires-Dist: flake8 >=6.0.0 ; extra == 'lint'
Requires-Dist: flake8-pyproject ; extra == 'lint'
Provides-Extra: test
Requires-Dist: coverage ; extra == 'test'
Requires-Dist: deepdiff >=1.7.0 ; extra == 'test'
Requires-Dist: pytest ; extra == 'test'
Requires-Dist: pytest-cov ; extra == 'test'
